nonlocalpooling/__init__.py
nonlocalpooling/pool.py
nonlocalpooling-2.0.1.dist-info/LICENSE
nonlocalpooling-2.0.1.dist-info/METADATA
nonlocalpooling-2.0.1.dist-info/WHEEL
nonlocalpooling-2.0.1.dist-info/top_level.txt
nonlocalpooling-2.0.1.dist-info/RECORD
