Metadata-Version: 2.1
Name: nonlocalpooling
Version: 2.0.1
Summary: Global-Wise Pooling Layers for PyTorch
Home-page: https://github.com/Dootmaan/NonLocalPooling
Author: Hongyi Wang
Author-email: whongyi@zju.edu.cn
Project-URL: Bug Tracker, https://github.com/Dootmaan/NonLocalPooling/issues
Classifier: Programming Language :: Python :: 3
Classifier: License :: OSI Approved :: MIT License
Classifier: Operating System :: OS Independent
Requires-Python: >=3.5
License-File: LICENSE
